wagtail_cache_invalidator/__init__.py
wagtail_cache_invalidator/admin_urls.py
wagtail_cache_invalidator/apps.py
wagtail_cache_invalidator/forms.py
wagtail_cache_invalidator/models.py
wagtail_cache_invalidator/settings.py
wagtail_cache_invalidator/signal_handlers.py
wagtail_cache_invalidator/signals.py
wagtail_cache_invalidator/utils.py
wagtail_cache_invalidator/views.py
wagtail_cache_invalidator/wagtail_hooks.py
wagtail_cache_invalidator/migrations/0001_initial.py
wagtail_cache_invalidator/migrations/0002_cachesettings.py
wagtail_cache_invalidator/migrations/0003_purgecachesite.py
wagtail_cache_invalidator/migrations/__init__.py
wagtail_cache_invalidator/templates/ wagtailcacheinvalidator/purge.html
wagtail_cache_invalidator-0.7.0.dist-info/METADATA
wagtail_cache_invalidator-0.7.0.dist-info/WHEEL
wagtail_cache_invalidator-0.7.0.dist-info/top_level.txt
wagtail_cache_invalidator-0.7.0.dist-info/RECORD
